{
	"e0f99ad33e8f7d5943321c0cac94aab0": {
		"type": "entry",
		"author": {
			"type": "card",
			"name": "Luke Blaney",
			"photo": "https://webmention.io/avatar/pbs.twimg.com/6b765eb2c3151af655e704c173b4ce2d764195d027002aace7cdf0e796d94620.jpg",
			"url": "https://twitter.com/lucas42"
		},
		"url": "https://twitter.com/rowanmanning/status/1426841859687686146#favorited-by-17844917",
		"published": null,
		"wm-received": "2021-08-15T10:34:32Z",
		"wm-id": 1247363,
		"wm-source": "https://brid.gy/like/twitter/rowanmanning/1426841859687686146/17844917",
		"wm-target": "https://rowanmanning.com/weeknotes/42/",
		"like-of": "https://rowanmanning.com/weeknotes/42/",
		"wm-property": "like-of",
		"wm-private": false
	},
	"4fcb51bc4a5b4075d452f489b6392285": {
		"type": "entry",
		"author": {
			"type": "card",
			"name": "Andrew Walker",
			"photo": "https://webmention.io/avatar/pbs.twimg.com/77ceb4604e68ec4eec61cbb303e8a19dfdd3cdf97b79024b41e2a0b81aa984de.gif",
			"url": "https://twitter.com/moddular"
		},
		"url": "https://twitter.com/rowanmanning/status/1426841859687686146#favorited-by-16433622",
		"published": null,
		"wm-received": "2021-08-15T10:34:38Z",
		"wm-id": 1247364,
		"wm-source": "https://brid.gy/like/twitter/rowanmanning/1426841859687686146/16433622",
		"wm-target": "https://rowanmanning.com/weeknotes/42/",
		"like-of": "https://rowanmanning.com/weeknotes/42/",
		"wm-property": "like-of",
		"wm-private": false
	},
	"50f5cd60f1ac9cc27a30c2a6d0ca2a18": {
		"type": "entry",
		"author": {
			"type": "card",
			"name": "Kinnoha",
			"photo": "https://webmention.io/avatar/pbs.twimg.com/7f661e1f3486b462b77da6008b4787db1aea0cf36a9421b5f3e6c6399f5e07f8.jpg",
			"url": "https://twitter.com/kinnoha"
		},
		"url": "https://twitter.com/kinnoha/status/1426847798675353603",
		"published": "2021-08-15T10:06:39+00:00",
		"wm-received": "2021-08-15T10:35:01Z",
		"wm-id": 1247365,
		"wm-source": "https://brid.gy/comment/twitter/rowanmanning/1426841859687686146/1426847798675353603",
		"wm-target": "https://rowanmanning.com/weeknotes/42/",
		"content": {
			"html": "Oh no, sorry to hear this, he was a cutie! 😞 rest in peace little Toots ❤️\n<a class=\"u-mention\" href=\"https://rowanmanning.com/\"></a>\n<a class=\"u-mention\" href=\"https://twitter.com/rowanmanning\"></a>",
			"text": "Oh no, sorry to hear this, he was a cutie! 😞 rest in peace little Toots ❤️"
		},
		"in-reply-to": "https://rowanmanning.com/weeknotes/42/",
		"wm-property": "in-reply-to",
		"wm-private": false
	},
	"e37d44d6db8fc94cee506b2c7a95ef6c": {
		"type": "entry",
		"author": {
			"type": "card",
			"name": "Lily",
			"photo": "https://webmention.io/avatar/pbs.twimg.com/2a2e63e98c493279264564c46275ecba152bab957c824eaaeff4271770c00db0.jpg",
			"url": "https://twitter.com/Lily_2point0"
		},
		"url": "https://twitter.com/Lily_2point0/status/1426846378597224448",
		"published": "2021-08-15T10:01:00+00:00",
		"wm-received": "2021-08-15T10:35:04Z",
		"wm-id": 1247366,
		"wm-source": "https://brid.gy/comment/twitter/rowanmanning/1426841859687686146/1426846378597224448",
		"wm-target": "https://rowanmanning.com/weeknotes/42/",
		"content": {
			"html": "Noooooo 😭😭😭\nSending hugs to you both\n<a class=\"u-mention\" href=\"https://rowanmanning.com/\"></a>\n<a class=\"u-mention\" href=\"https://twitter.com/rowanmanning\"></a>",
			"text": "Noooooo 😭😭😭\nSending hugs to you both"
		},
		"in-reply-to": "https://rowanmanning.com/weeknotes/42/",
		"wm-property": "in-reply-to",
		"wm-private": false
	},
	"dae6f3a16272248e141146d84b0f50ce": {
		"type": "entry",
		"author": {
			"type": "card",
			"name": "Amy Hupe",
			"photo": "https://webmention.io/avatar/pbs.twimg.com/f502c245e5e79440c1368cb683c0e8a3579399b9e1e4137297b9e1d8e45f1f08.jpg",
			"url": "https://twitter.com/Amy_Hupe"
		},
		"url": "https://twitter.com/Amy_Hupe/status/1426879173549768708",
		"published": "2021-08-15T12:11:19+00:00",
		"wm-received": "2021-08-15T12:13:36Z",
		"wm-id": 1247399,
		"wm-source": "https://brid.gy/comment/twitter/rowanmanning/1426841859687686146/1426879173549768708",
		"wm-target": "https://rowanmanning.com/weeknotes/42/",
		"content": {
			"html": "💔 what a beautiful cat. Looks like you gave him a very lovely life.\n<a class=\"u-mention\" href=\"https://rowanmanning.com/\"></a>\n<a class=\"u-mention\" href=\"https://twitter.com/rowanmanning\"></a>",
			"text": "💔 what a beautiful cat. Looks like you gave him a very lovely life."
		},
		"in-reply-to": "https://rowanmanning.com/weeknotes/42/",
		"wm-property": "in-reply-to",
		"wm-private": false
	},
	"a5ce0d29e9f753fd047df1145f187998": {
		"type": "entry",
		"author": {
			"type": "card",
			"name": "Oliver 🏖",
			"photo": "https://webmention.io/avatar/pbs.twimg.com/bb6054dd4e7cdd1650eabe48cb06ec5c9617e2878b15fd9abc26296b0b754c37.jpg",
			"url": "https://twitter.com/oliverturner"
		},
		"url": "https://twitter.com/rowanmanning/status/1426841859687686146#favorited-by-14652753",
		"published": null,
		"wm-received": "2021-08-15T12:13:38Z",
		"wm-id": 1247401,
		"wm-source": "https://brid.gy/like/twitter/rowanmanning/1426841859687686146/14652753",
		"wm-target": "https://rowanmanning.com/weeknotes/42/",
		"like-of": "https://rowanmanning.com/weeknotes/42/",
		"wm-property": "like-of",
		"wm-private": false
	},
	"709602b3c132e66725c7270adbc14ce0": {
		"type": "entry",
		"author": {
			"type": "card",
			"name": "arjun",
			"photo": "https://webmention.io/avatar/pbs.twimg.com/375093eb9cf3616b135b656a2011a5d33a95d547381704557961e733eef4a7c2.jpg",
			"url": "https://twitter.com/adgad"
		},
		"url": "https://twitter.com/adgad/status/1426875592759197696",
		"published": "2021-08-15T11:57:06+00:00",
		"wm-received": "2021-08-15T12:13:38Z",
		"wm-id": 1247400,
		"wm-source": "https://brid.gy/comment/twitter/rowanmanning/1426841859687686146/1426875592759197696",
		"wm-target": "https://rowanmanning.com/weeknotes/42/",
		"content": {
			"html": "😭🫂\n<a class=\"u-mention\" href=\"https://rowanmanning.com/\"></a>\n<a class=\"u-mention\" href=\"https://twitter.com/rowanmanning\"></a>",
			"text": "😭🫂"
		},
		"in-reply-to": "https://rowanmanning.com/weeknotes/42/",
		"wm-property": "in-reply-to",
		"wm-private": false
	},
	"8bd3cadc382c89373d4e582059a21cbe": {
		"type": "entry",
		"author": {
			"type": "card",
			"name": "Amir TG",
			"photo": "https://webmention.io/avatar/pbs.twimg.com/08c5a88f759a139905747a8c8c136919dd4f331ae8a69219da1dbeb8f7167609.jpg",
			"url": "https://twitter.com/AmirTG1"
		},
		"url": "https://twitter.com/AmirTG1/status/1426880934607998978",
		"published": "2021-08-15T12:18:19+00:00",
		"wm-received": "2021-08-15T12:20:13Z",
		"wm-id": 1247405,
		"wm-source": "https://brid.gy/comment/twitter/rowanmanning/1426841859687686146/1426880934607998978",
		"wm-target": "https://rowanmanning.com/weeknotes/42/",
		"content": {
			"html": "So sorry to hear that 😭\n<a class=\"u-mention\" href=\"https://rowanmanning.com/\"></a>\n<a class=\"u-mention\" href=\"https://twitter.com/rowanmanning\"></a>",
			"text": "So sorry to hear that 😭"
		},
		"in-reply-to": "https://rowanmanning.com/weeknotes/42/",
		"wm-property": "in-reply-to",
		"wm-private": false
	}
}